README.md
setup.cfg
setup.py
miotools/Config.py
miotools/Lock.py
miotools/Log.py
miotools/Profiler.py
miotools/SentryClient.py
miotools/Utils.py
miotools/__init__.py
miotools.egg-info/PKG-INFO
miotools.egg-info/SOURCES.txt
miotools.egg-info/dependency_links.txt
miotools.egg-info/not-zip-safe
miotools.egg-info/requires.txt
miotools.egg-info/top_level.txt