Metadata-Version: 1.0
Name: miotools
Version: 0.1.1
Summary: mioying util tools for python
Home-page: https://github.com/mioying/miotools
Author: miotech
Author-email: tech@mioying.com
License: MIT
Platform: UNKNOWN
